{"code":0,"message":"OK","data":{"records":[{"_createdAt":1724837698334,"_id":"66ceef43af5771f18c5013e8","_updatedAt":1749563101824,"data":{"bigrank":"7","camp_type":"0","main_hero":{"data":{"head":"https://akmweb.youngjoygame.com/web/svnres/img/mlbb/homepage_92/100_595f85bc90df3889c711c6b1f02dc02d.png","name":"Zhuxin"}},"main_hero_appearance_rate":0.003283,"main_hero_ban_rate":0.179357,"main_hero_channel":{"id":2727282},"main_hero_win_rate":0.501517,"main_heroid":125,"match_type":"0","sub_hero":[{"hero":{"data":{"head":"https://akmweb.youngjoygame.com/web/svnres/img/mlbb/homepage/100_474cea36a4bfdc7bf7d94530853a99b2.png"}},"hero_appearance_rate":0.00152,"hero_channel":{"id":2678756},"hero_index":1,"hero_win_rate":0.612663,"heroid":20,"increase_win_rate":0.047571,"min_win_rate10_12":0.404092,"min_win_rate12_14":0.442748,"min_win_rate14_16":0.420183,"min_win_rate16_18":0.489189,"min_win_rate18_20":0.445783,"min_win_rate20":0.428977,"min_win_rate6":1,"min_win_rate6_8":0.384615,"min_win_rate8_10":0.415094},{"hero":{"data":{"head":"https://akmweb.youngjoygame.com/web/svnres/img/mlbb/homepage/100_fbb5065b6ff174d1a20ccf5b7f523514.png"}},"hero_appearance_rate":0.003827,"hero_channel":{"id":2678760},"hero_index":2,"hero_win_rate":0.492528,"heroid":24,"increase_win_rate":0.031558,"min_win_rate10_12":0.641975,"min_win_rate12_14":0.587323,"min_win_rate14_16":0.542572,"min_win_rate16_18":0.515425,"min_win_rate18_20":0.509453,"min_win_rate20":0.459005,"min_win_rate6":0,"min_win_rate6_8":0.545455,"min_win_rate8_10":0.68595},{"hero":{"data":{"head":"https://akmweb.youngjoygame.com/web/svnres/img/mlbb/homepage/100_554cdf13a7587fe08c5deed60132c61c.png"}},"hero_appearance_rate":0.001731,"hero_channel":{"id":2678803},"hero_index":3,"hero_win_rate":0.51127,"heroid":67,"increase_win_rate":0.02563,"min_win_rate10_12":0.511754,"min_win_rate12_14":0.502415,"min_win_rate14_16":0.50989,"min_win_rate16_18":0.547264,"min_win_rate18_20":0.518764,"min_win_rate20":0.507087,"min_win_rate6":0,"min_win_rate6_8":0.517241,"min_win_rate8_10":0.566265},{"hero":{"data":{"head":"https://akmweb.youngjoygame.com/web/svnres/img/mlbb/homepage/100_b3a7602fe7ffd1e54bf8ea79ceadfa72.png"}},"hero_appearance_rate":0.006129,"hero_channel":{"id":2678845},"hero_index":4,"hero_win_rate":0.493937,"heroid":109,"increase_win_rate":0.023544,"min_win_rate10_12":0.571194,"min_win_rate12_14":0.568752,"min_win_rate14_16":0.539403,"min_win_rate16_18":0.519088,"min_win_rate18_20":0.48911,"min_win_rate20":0.47018,"min_win_rate6":1,"min_win_rate6_8":0.537037,"min_win_rate8_10":0.58805},{"hero":{"data":{"head":"https://akmweb.youngjoygame.com/web/svnres/img/mlbb/homepage/100_6495be044c2d28106e200f6918391d54.png"}},"hero_appearance_rate":0.001417,"hero_channel":{"id":2678835},"hero_index":5,"hero_win_rate":0.510351,"heroid":99,"increase_win_rate":0.020429,"min_win_rate10_12":0.495833,"min_win_rate12_14":0.475036,"min_win_rate14_16":0.522816,"min_win_rate16_18":0.517103,"min_win_rate18_20":0.517711,"min_win_rate20":0.54461,"min_win_rate6":0,"min_win_rate6_8":0.481481,"min_win_rate8_10":0.547945}],"sub_hero_last":[{"hero":{"data":{"head":"https://akmweb.youngjoygame.com/web/svnres/img/mlbb/homepage/100_04e575d648d7f7ac1174f4369595c3a2.png"}},"hero_appearance_rate":0.000356,"hero_channel":{"id":2678812},"hero_index":1,"hero_win_rate":0.470003,"heroid":76,"increase_win_rate":-0.043136,"min_win_rate10_12":0.559701,"min_win_rate12_14":0.5,"min_win_rate14_16":0.479769,"min_win_rate16_18":0.5,"min_win_rate18_20":0.360465,"min_win_rate20":0.441667,"min_win_rate6":0,"min_win_rate6_8":0.555556,"min_win_rate8_10":0.681818},{"hero":{"data":{"head":"https://akmweb.youngjoygame.com/web/svnres/img/mlbb/homepage/100_d8f170087cb2d5b71bb22a0a4664a927.png"}},"hero_appearance_rate":0.006251,"hero_channel":{"id":2678786},"hero_index":2,"hero_win_rate":0.526662,"heroid":50,"increase_win_rate":-0.030197,"min_win_rate10_12":0.422619,"min_win_rate12_14":0.430363,"min_win_rate14_16":0.448033,"min_win_rate16_18":0.453613,"min_win_rate18_20":0.456224,"min_win_rate20":0.463518,"min_win_rate6":0,"min_win_rate6_8":0.517241,"min_win_rate8_10":0.401235},{"hero":{"data":{"head":"https://akmweb.youngjoygame.com/web/svnres/img/mlbb/homepage/100_b2b38e9406ea0de0b866db7674feea0f.png"}},"hero_appearance_rate":0.033433,"hero_channel":{"id":2678754},"hero_index":3,"hero_win_rate":0.509869,"heroid":18,"increase_win_rate":-0.019113,"min_win_rate10_12":0.559053,"min_win_rate12_14":0.482965,"min_win_rate14_16":0.459741,"min_win_rate16_18":0.433011,"min_win_rate18_20":0.43054,"min_win_rate20":0.442432,"min_win_rate6":1,"min_win_rate6_8":0.649805,"min_win_rate8_10":0.626481},{"hero":{"data":{"head":"https://akmweb.youngjoygame.com/web/svnres/img/mlbb/homepage/100_bf16690876761b80822df90eb3320d69.png"}},"hero_appearance_rate":0.009136,"hero_channel":{"id":2678793},"hero_index":4,"hero_win_rate":0.507066,"heroid":57,"increase_win_rate":-0.018841,"min_win_rate10_12":0.460317,"min_win_rate12_14":0.489485,"min_win_rate14_16":0.486949,"min_win_rate16_18":0.485462,"min_win_rate18_20":0.456239,"min_win_rate20":0.451554,"min_win_rate6":1,"min_win_rate6_8":0.585366,"min_win_rate8_10":0.502747},{"hero":{"data":{"head":"https://akmweb.youngjoygame.com/web/svnres/img/mlbb/homepage/100_5f2a9eca0bafd4ed8dc39a93c771b3af.png"}},"hero_appearance_rate":0.011664,"hero_channel":{"id":2678806},"hero_index":5,"hero_win_rate":0.541701,"heroid":70,"increase_win_rate":-0.016985,"min_win_rate10_12":0.426894,"min_win_rate12_14":0.448529,"min_win_rate14_16":0.446036,"min_win_rate16_18":0.435639,"min_win_rate18_20":0.440925,"min_win_rate20":0.448466,"min_win_rate6":0,"min_win_rate6_8":0.458564,"min_win_rate8_10":0.463312}]},"id":103525,"sourceId":2756569}],"total":1}}